enkryptai_sdk/__init__.py
enkryptai_sdk/ai_proxy.py
enkryptai_sdk/base.py
enkryptai_sdk/coc.py
enkryptai_sdk/config.py
enkryptai_sdk/datasets.py
enkryptai_sdk/deployments.py
enkryptai_sdk/evals.py
enkryptai_sdk/guardrails.py
enkryptai_sdk/guardrails_old.py
enkryptai_sdk/models.py
enkryptai_sdk/red_team.py
enkryptai_sdk/response.py
enkryptai_sdk/dto/__init__.py
enkryptai_sdk/dto/ai_proxy.py
enkryptai_sdk/dto/base.py
enkryptai_sdk/dto/coc.py
enkryptai_sdk/dto/common.py
enkryptai_sdk/dto/datasets.py
enkryptai_sdk/dto/deployments.py
enkryptai_sdk/dto/guardrails.py
enkryptai_sdk/dto/models.py
enkryptai_sdk/dto/red_team.py
enkryptai_sdk/utils/__init__.py
enkryptai_sdk/utils/pagination.py
enkryptai_sdk-1.0.26.dist-info/licenses/LICENSE
enkryptai_sdk-1.0.26.dist-info/METADATA
enkryptai_sdk-1.0.26.dist-info/WHEEL
enkryptai_sdk-1.0.26.dist-info/top_level.txt
enkryptai_sdk-1.0.26.dist-info/RECORD
